CHANGES
LICENSE
MANIFEST.in
README.rst
setup.cfg
setup.py
briefcase/__init__.py
briefcase/admin.py
briefcase/models.py
briefcase/tests.py
briefcase/data/mime.types
briefcase/fixtures/document_statuses.json
briefcase/fixtures/document_types.json
briefcase/migrations/0001_initial.py
briefcase/migrations/0002_auto__chg_field_document_file.py
briefcase/migrations/0003_auto__add_documenttype.py
briefcase/migrations/0004_auto__add_field_document_type.py
briefcase/migrations/0005_default_document_type.py
briefcase/migrations/0006_auto__chg_field_document_type.py
briefcase/migrations/0007_auto__chg_field_document_type__add_field_documenttype_extension.py
briefcase/migrations/__init__.py
briefcase/templatetags/__init__.py
briefcase/templatetags/document_tags.py
briefcase/views/__init__.py
briefcase/views/general.py
briefcase/views/per_user.py
django_briefcase.egg-info/PKG-INFO
django_briefcase.egg-info/SOURCES.txt
django_briefcase.egg-info/dependency_links.txt
django_briefcase.egg-info/not-zip-safe
django_briefcase.egg-info/requires.txt
django_briefcase.egg-info/top_level.txt