Metadata-Version: 1.0
Name: django-briefcase
Version: 0.1b2
Summary: Yet another document management app for Django.
Home-page: http://github.com/zsiciarz/django-briefcase
Author: Zbigniew Siciarz
Author-email: antyqjon@gmail.com
License: MIT
Platform: UNKNOWN
Classifier: Development Status :: 4 - Beta
Classifier: Environment :: Web Environment
Classifier: Framework :: Django
Classifier: Intended Audience :: Developers
Classifier: License :: OSI Approved :: MIT License
Classifier: Operating System :: OS Independent
Classifier: Programming Language :: Python
Classifier: Topic :: Utilities
